{"chunk_definitions":[{"row":43,"row_count":1,"visible":true,"expansion_state":0,"options":{"engine":"r","label":"unnamed-chunk-86"},"document_id":"6271EEF2","chunk_id":"cq60x2nomq62q","chunk_label":"unnamed-chunk-1"},{"row":52,"row_count":1,"visible":true,"expansion_state":0,"options":{"engine":"r","label":"unnamed-chunk-36"},"document_id":"6271EEF2","chunk_id":"c38j1q13ud68z","chunk_label":"unnamed-chunk-2"},{"row":82,"row_count":1,"visible":true,"expansion_state":0,"options":{"engine":"r","label":"unnamed-chunk-37"},"document_id":"6271EEF2","chunk_id":"cz0i915ojr40r","chunk_label":"unnamed-chunk-3"},{"row":94,"row_count":1,"visible":true,"expansion_state":0,"options":{"engine":"r","label":"unnamed-chunk-55"},"document_id":"6271EEF2","chunk_id":"cke620bs11uye","chunk_label":"unnamed-chunk-4"},{"row":143,"row_count":1,"visible":true,"expansion_state":0,"options":{"engine":"r","label":"unnamed-chunk-83"},"document_id":"6271EEF2","chunk_id":"cgcetw3psyabo","chunk_label":"unnamed-chunk-5"},{"row":179,"row_count":1,"visible":true,"expansion_state":0,"options":{"engine":"r","label":"unnamed-chunk-84"},"document_id":"6271EEF2","chunk_id":"cc7tnkg9o6ffr","chunk_label":"unnamed-chunk-6"},{"row":303,"row_count":1,"visible":true,"expansion_state":0,"options":{"engine":"r","label":"unnamed-chunk-10"},"document_id":"6271EEF2","chunk_id":"chl6qswiem1od","chunk_label":"unnamed-chunk-7"},{"row":336,"row_count":1,"visible":true,"expansion_state":0,"options":{"engine":"r","label":"unnamed-chunk-91"},"document_id":"6271EEF2","chunk_id":"cplme3eulgyqo","chunk_label":"unnamed-chunk-8"},{"row":392,"row_count":1,"visible":true,"expansion_state":0,"options":{"engine":"r","label":"unnamed-chunk-90"},"document_id":"6271EEF2","chunk_id":"chud6ko7bq543","chunk_label":"unnamed-chunk-9"},{"row":424,"row_count":1,"visible":true,"expansion_state":0,"options":{"engine":"r","label":"unnamed-chunk-88"},"document_id":"6271EEF2","chunk_id":"co3yfjdk7dj8y","chunk_label":"unnamed-chunk-10"}],"doc_write_time":1659877837}