{"chunk_definitions":[{"row":24,"row_count":1,"visible":true,"expansion_state":0,"options":{"engine":"r","label":"unnamed-chunk-1"},"document_id":"DAB0DC62","chunk_id":"c7f6orx2c1it1","chunk_label":"unnamed-chunk-1"},{"row":115,"row_count":1,"visible":true,"expansion_state":0,"options":{"engine":"r","label":"unnamed-chunk-2"},"document_id":"DAB0DC62","chunk_id":"ch88qm8ak4qaq","chunk_label":"unnamed-chunk-2"},{"row":201,"row_count":1,"visible":true,"expansion_state":0,"options":{"engine":"r","label":"unnamed-chunk-9"},"document_id":"DAB0DC62","chunk_id":"cm4gfgctzy203","chunk_label":"unnamed-chunk-4"},{"row":224,"row_count":1,"visible":true,"expansion_state":0,"options":{"engine":"r","label":"unnamed-chunk-10"},"document_id":"DAB0DC62","chunk_id":"cpw0a5bxobj26","chunk_label":"unnamed-chunk-6"}],"doc_write_time":1661097886}